mvdate/__init__.py
mvdate/_version.py
mvdate/mvdate.py
mvdate-0.1.2.dist-info/COPYING
mvdate-0.1.2.dist-info/METADATA
mvdate-0.1.2.dist-info/WHEEL
mvdate-0.1.2.dist-info/entry_points.txt
mvdate-0.1.2.dist-info/top_level.txt
mvdate-0.1.2.dist-info/RECORD
