Metadata-Version: 2.1
Name: mvdate
Version: 0.1.2
Summary: Move files to directories based on created date
Author-email: Neil Shephard <nshephard@gmail.com>
License: GNU Lesser GPLv3 only
Project-URL: Source, https://gitlab.com/nshephard/mvdate
Project-URL: Bug_Tracker, https://gitlab.com/nshephard/mvdate/issues
Keywords: files,date
Classifier: Programming Language :: Python :: 3
Classifier: Programming Language :: Python :: 3.8
Classifier: Programming Language :: Python :: 3.9
Classifier: Programming Language :: Python :: 3.10
Classifier: Programming Language :: Python :: 3.11
Classifier: Programming Language :: Python :: 3.12
Classifier: Natural Language :: English
Classifier: Operating System :: OS Independent
Classifier: License :: OSI Approved :: GNU Lesser General Public License v3 (LGPLv3)
Requires-Python: >=3.8
License-File: COPYING
Requires-Dist: loguru
Requires-Dist: tqdm
Requires-Dist: pillow
Requires-Dist: pyfiglet
Provides-Extra: dev
Requires-Dist: codespell ; extra == 'dev'
Requires-Dist: Flake8-pyproject ; extra == 'dev'
Requires-Dist: black ; extra == 'dev'
Requires-Dist: flake8 ; extra == 'dev'
Requires-Dist: flake8-print ; extra == 'dev'
Requires-Dist: mypy ; extra == 'dev'
Requires-Dist: pre-commit ; extra == 'dev'
Requires-Dist: pylint ; extra == 'dev'
Requires-Dist: pyupgrade ; extra == 'dev'
Requires-Dist: pytest-durations ; extra == 'dev'
Requires-Dist: pytest-xdist ; extra == 'dev'
Requires-Dist: ruff ; extra == 'dev'
Requires-Dist: tracelogger ; extra == 'dev'
Provides-Extra: docs
Requires-Dist: Sphinx ; extra == 'docs'
Requires-Dist: myst-parser ; extra == 'docs'
Requires-Dist: numpydoc ; extra == 'docs'
Requires-Dist: pydata-sphinx-theme ; extra == 'docs'
Requires-Dist: sphinx-autoapi ; extra == 'docs'
Requires-Dist: sphinx-autodoc-typehints ; extra == 'docs'
Requires-Dist: sphinx-multiversion ; extra == 'docs'
Requires-Dist: sphinx-markdown-tables ; extra == 'docs'
Requires-Dist: sphinx-rtd-theme ; extra == 'docs'
Requires-Dist: sphinxcontrib-mermaid ; extra == 'docs'
Requires-Dist: sphinxcontrib-napoleon ; extra == 'docs'
Provides-Extra: pypi
Requires-Dist: build ; extra == 'pypi'
Requires-Dist: wheel ; extra == 'pypi'
Requires-Dist: setuptools-scm[toml] ; extra == 'pypi'
Requires-Dist: twine ; extra == 'pypi'
Provides-Extra: tests
Requires-Dist: py ; extra == 'tests'
Requires-Dist: pytest ; extra == 'tests'
Requires-Dist: pytest-cov ; extra == 'tests'
Requires-Dist: pytest-mpl ; extra == 'tests'
Requires-Dist: pytest-tmp-files ; extra == 'tests'
Requires-Dist: filetype ; extra == 'tests'
